pingpong/__init__.py
pingpong/alpaca.py
pingpong/gradio.py
pingpong/pingpong.py
piingpoong-0.0.1.dist-info/LICENSE
piingpoong-0.0.1.dist-info/METADATA
piingpoong-0.0.1.dist-info/WHEEL
piingpoong-0.0.1.dist-info/top_level.txt
piingpoong-0.0.1.dist-info/RECORD
