Metadata-Version: 2.1
Name: piingpoong
Version: 0.0.1
Summary: Ping pong management library for LLM applied application
Home-page: https://github.com/deep-diver/PingPong
Author: chansung park
Author-email: deep.diver.csp@gmail.com
Keywords: LLM,pingpong,prompt,context,management
Classifier: License :: OSI Approved :: Apache Software License
Classifier: Programming Language :: Python :: 3.8
Classifier: Programming Language :: Python :: 3.9
Classifier: Programming Language :: Python :: 3.10
Classifier: Programming Language :: Python :: 3.11
License-File: LICENSE
